itgeeker/__init__.py
itgeeker/date_geeker.py
itgeeker/ffp_geeker.py
itgeeker/format_geeker.py
itgeeker/geeker_api.py
itgeeker/geekermaster_parse.py
itgeeker/main.py
itgeeker/odoo_geeker.py
itgeeker/redis_geeker.py
itgeeker/sign_geeker.py
itgeeker/sys_geeker.py
itgeeker-0.2.6.dist-info/METADATA
itgeeker-0.2.6.dist-info/WHEEL
itgeeker-0.2.6.dist-info/RECORD
