Metadata-Version: 2.4
Name: itgeeker
Version: 0.2.6
Summary: Build by ITGeeker.net
Author: ITGeeker
Requires-Python: >=3.12
Requires-Dist: chardet>=5.2.0
Requires-Dist: pytz>=2025.2
Requires-Dist: requests>=2.32.4
